<?xml version="1.0" encoding="UTF-8"?>
<!-- edited with XML Spy v4.4 U (http://www.xmlspy.com) by mjoaquim (CSC Financial Services Group) -->
<TXLife xmlns:xsi="http://www.w3.org/2001/XMLSchema-instance" xmlns="http://ACORD.org/Standards/Life/2" xsi:noNamespaceSchemaLocation="C:\XMLGateway\schemafiles\TXLife2.8.92.xsd">
	<TXLifeRequest>
		<TransRefGUID>RoleAdd</TransRefGUID>
		<TransType tc="502"/>
		<ChangeSubType ChangeID="Relation_1" id="change_1">
			<ChangeTC tc="22">Role</ChangeTC>
			<TranContentCode tc="1"/>
			<ElementName>RelationRoleCode</ElementName>
		</ChangeSubType>
		<OLifE>
			<Activity id="Activity_1">
				<ActivityDetails>ssss</ActivityDetails>
				<ScheduledChange>
					<ReversalInd tc="0"/>
				</ScheduledChange>
			</Activity>
			<Holding id="Holding_1">
				<Policy>
					<PolNumber>enh1091roletrad</PolNumber>
					<CarrierCode>VCS</CarrierCode>
				</Policy>
				<OLifEExtension VendorCode="">
					<HoldingExtension>
						<RestrictionInfo id="Restriction_1">
							<RestrictionReason tc="2">2</RestrictionReason>
							<StartDate>2008-02-02</StartDate>
							<TaxableType tc="1000500009"/>
							<TaxPenaltyInd tc="1">1</TaxPenaltyInd>
							<TaxFormOverride tc="0">0</TaxFormOverride>
							<AssignmentMailCodeInd tc="0">0</AssignmentMailCodeInd>
						</RestrictionInfo>
					</HoldingExtension>
				</OLifEExtension>
			</Holding>
			<Party id="party_1">
			      <PartyTypeCode tc="1"/>
				<PartyKey Persist="Session"/>
				<FullName/>
				<GovtID>555660923</GovtID>
				<GovtIDStat tc="1"/>
				<GovtIDTC tc="1"/>
				<ResidenceState tc="8"/>
				<ResidenceCounty/>
				<ResidenceZip/> 
				<IDReferenceNo>419419419</IDReferenceNo>
				<Person>
					<FirstName>RANJEET</FirstName>
					<LastName>KUMAR</LastName>
					<Prefix/>
					<Suffix/>
					<Gender tc="2"/>
					<BirthDate>1949-04-19</BirthDate>
				</Person>
				<Address>
					<Line1>98 MAIN ST</Line1>
					<City>AVON</City>
					<AddressStateTC tc="8"/>
					<Zip>06001</Zip>
					<AddressCountryTC tc="1"/>
				</Address>
			</Party>
			<Relation id="Relation_1" OriginatingObjectID="Holding_1" RelatedObjectID="party_1">
				<RelationRoleCode tc="145">145</RelationRoleCode>
			</Relation>
		</OLifE>
	</TXLifeRequest>
</TXLife>
